data/__init__.py
docs/__init__.py
models/__init__.py
models/CIFAR10/__init__.py
pruningdistribution/__init__.py
pruningdistribution/custom_dataset.py
pruningdistribution/metrics.py
pruningdistribution/model_params.py
pruningdistribution/pruning_utils.py
pruningdistribution/train.py
results/__init__.py
test/__init__.py
pruningdistribution-0.1.0.dist-info/LICENSE
pruningdistribution-0.1.0.dist-info/METADATA
pruningdistribution-0.1.0.dist-info/WHEEL
pruningdistribution-0.1.0.dist-info/top_level.txt
pruningdistribution-0.1.0.dist-info/RECORD
