Metadata-Version: 2.1
Name: pruningdistribution
Version: 0.1.0
Summary: Pruning of CNNs with distributions
Home-page: https://github.com/DEEP-CGPS/PruningDistribution
Author: DEEP-CGPS
Author-email: <est.cesar.pachon@unimilitar.edu.co>
Keywords: python,pytorch,pruning,CNN,distribution,FLOPs
Requires-Python: >=3.6
License-File: LICENSE
Requires-Dist: torch
Requires-Dist: torchvision
